pdbrust/__init__.py
pdbrust/_pdbrust.cpython-310-darwin.so
pdbrust/py.typed
pdbrust-0.6.0.dist-info/METADATA
pdbrust-0.6.0.dist-info/WHEEL
pdbrust-0.6.0.dist-info/RECORD
