Metadata-Version: 2.4
Name: pdbrust
Version: 0.6.0
Classifier: Development Status :: 4 - Beta
Classifier: Intended Audience :: Science/Research
Classifier: License :: OSI Approved :: MIT License
Classifier: Programming Language :: Python :: 3
Classifier: Programming Language :: Python :: 3.9
Classifier: Programming Language :: Python :: 3.10
Classifier: Programming Language :: Python :: 3.11
Classifier: Programming Language :: Python :: 3.12
Classifier: Programming Language :: Python :: 3.13
Classifier: Programming Language :: Rust
Classifier: Topic :: Scientific/Engineering :: Bio-Informatics
Classifier: Topic :: Scientific/Engineering :: Chemistry
Requires-Dist: pytest>=7.0 ; extra == 'dev'
Requires-Dist: numpy>=1.20 ; extra == 'dev'
Requires-Dist: numpy>=1.20 ; extra == 'numpy'
Provides-Extra: dev
Provides-Extra: numpy
Summary: High-performance PDB/mmCIF parsing and analysis library with Python bindings
Keywords: pdb,protein,bioinformatics,structural-biology,mmcif,parsing
Home-Page: https://github.com/HFooladi/pdbrust
Author-email: Hosein Fooladi <fooladi.hosein@gmail.com>
License: MIT
Requires-Python: >=3.9
Project-URL: Documentation, https://docs.rs/pdbrust
Project-URL: Homepage, https://github.com/HFooladi/pdbrust
Project-URL: Repository, https://github.com/HFooladi/pdbrust
